{
    "imageListData": {
        "type": "object",
        "objectId": "imageListSample",
        "title": "Bem vindo a Nutriclinic",
        "listItems": [
            {
                "primaryText": "Servicos",
                "secondaryText": "Conheca nossos Servicos",
                "tertiaryText": "Diga Conhecer Servicos",
                "tertiaryTextPosition": "top",
                "imageAlignment": "left",
                "imageSource": "https://undercontrol.blob.core.windows.net/alexa/massage.png",
                "primaryAction": [
                    {
                        "type": "SetValue",
                        "componentId": "menuList",
                        "property": "headerTitle",
                        "value": "${payload.imageListData.listItems[2].primaryText} is selected"
                    }
                ]
            },
            {
                "primaryText": "Agendamento",
                "secondaryText": "Agenda uma consulta agora mesmo",
                "tertiaryText": "Diga Fazer Agendamento",
                "tertiaryTextPosition": "top",
                "imageAlignment": "left",
                "imageSource": "https://undercontrol.blob.core.windows.net/alexa/noun_REIKI_2677052.png",
                "primaryAction": [
                    {
                        "type": "SetValue",
                        "componentId": "cheeseList",
                        "property": "headerTitle",
                        "value": "${payload.imageListData.listItems[2].primaryText} is selected"
                    }
                ]
            },
            {
                "primaryText": "Horario de Funcionamento",
                "secondaryText": "Saiba nosso horario de funcionamento",
                "tertiaryText": "Diga Horario de Funcionamento",
                "tertiaryTextPosition": "top",
                "imageAlignment": "left",
                "imageSource": "https://undercontrol.blob.core.windows.net/alexa/noun_acupuncture_2677049.png",
                "primaryAction": [
                    {
                        "type": "SetValue",
                        "componentId": "cheeseList",
                        "property": "headerTitle",
                        "value": "${payload.imageListData.listItems[2].primaryText} is selected"
                    }
                ]
            },
            {
                "primaryText": "Recado",
                "secondaryText": "Para Informacao ou Recado",
                "tertiaryText": "Diga Deixar Recado",
                "tertiaryTextPosition": "top",
                "imageAlignment": "left",
                "imageSource": "https://undercontrol.blob.core.windows.net/alexa/noun_REIKI_2677052.png",
                "primaryAction": [
                    {
                        "type": "SetValue",
                        "componentId": "cheeseList",
                        "property": "headerTitle",
                        "value": "${payload.imageListData.listItems[2].primaryText} is selected"
                    }
                ]
            }
      
        ],
        "logoUrl": "https://d2o906d8ln7ui1.cloudfront.net/images/templates_v2/icon_cheese.png",
        "hintText": "Tente, \"Alexa, exibir detalhes Acumputura\""
    }
}